nalkinscloud_mqtt_python_client/__init__.py
nalkinscloud_mqtt_python_client/devices.py
nalkinscloud_mqtt_python_client/mqtt_handler.py
test/__init__.py
test/test_client_handler.py
nalkinscloud_mqtt_python_client-1.0.3.dist-info/LICENSE
nalkinscloud_mqtt_python_client-1.0.3.dist-info/METADATA
nalkinscloud_mqtt_python_client-1.0.3.dist-info/WHEEL
nalkinscloud_mqtt_python_client-1.0.3.dist-info/top_level.txt
nalkinscloud_mqtt_python_client-1.0.3.dist-info/RECORD
