Metadata-Version: 2.1
Name: nalkinscloud-mqtt-python-client
Version: 1.0.3
Summary: Simple MQTT client implementation that fits nalkinscloud projects
Home-page: https://github.com/ArieLevs/nalkinscloud-mqtt-python-client
Author: Arie Lev
Author-email: levinson.arie@gmail.com
License: UNKNOWN
Platform: UNKNOWN
Classifier: Programming Language :: Python :: 3
Classifier: Programming Language :: Python :: 3.8
Classifier: License :: OSI Approved :: MIT License
Classifier: Operating System :: OS Independent
Requires-Dist: paho-mqtt (==1.5.1)
